pyinjective/Peggo_ABI.json
pyinjective/__init__.py
pyinjective/async_client.py
pyinjective/async_client_v2.py
pyinjective/client/__init__.py
pyinjective/client/chain/__init__.py
pyinjective/client/chain/grpc/__init__.py
pyinjective/client/chain/grpc/chain_grpc_auction_api.py
pyinjective/client/chain/grpc/chain_grpc_auth_api.py
pyinjective/client/chain/grpc/chain_grpc_authz_api.py
pyinjective/client/chain/grpc/chain_grpc_bank_api.py
pyinjective/client/chain/grpc/chain_grpc_distribution_api.py
pyinjective/client/chain/grpc/chain_grpc_erc20_api.py
pyinjective/client/chain/grpc/chain_grpc_evm_api.py
pyinjective/client/chain/grpc/chain_grpc_exchange_api.py
pyinjective/client/chain/grpc/chain_grpc_exchange_v2_api.py
pyinjective/client/chain/grpc/chain_grpc_permissions_api.py
pyinjective/client/chain/grpc/chain_grpc_token_factory_api.py
pyinjective/client/chain/grpc/chain_grpc_txfees_api.py
pyinjective/client/chain/grpc/chain_grpc_wasm_api.py
pyinjective/client/chain/grpc_stream/__init__.py
pyinjective/client/chain/grpc_stream/chain_grpc_chain_stream.py
pyinjective/client/chain/model/__init__.py
pyinjective/client/chain/model/account.py
pyinjective/client/chain/model/auth_params.py
pyinjective/client/indexer/__init__.py
pyinjective/client/indexer/grpc/__init__.py
pyinjective/client/indexer/grpc/indexer_grpc_account_api.py
pyinjective/client/indexer/grpc/indexer_grpc_auction_api.py
pyinjective/client/indexer/grpc/indexer_grpc_derivative_api.py
pyinjective/client/indexer/grpc/indexer_grpc_explorer_api.py
pyinjective/client/indexer/grpc/indexer_grpc_insurance_api.py
pyinjective/client/indexer/grpc/indexer_grpc_meta_api.py
pyinjective/client/indexer/grpc/indexer_grpc_oracle_api.py
pyinjective/client/indexer/grpc/indexer_grpc_portfolio_api.py
pyinjective/client/indexer/grpc/indexer_grpc_spot_api.py
pyinjective/client/indexer/grpc_stream/__init__.py
pyinjective/client/indexer/grpc_stream/indexer_grpc_account_stream.py
injective_py-1.12.0.dist-info/METADATA
injective_py-1.12.0.dist-info/WHEEL
injective_py-1.12.0.dist-info/licenses/LICENSE.md
injective_py-1.12.0.dist-info/licenses/NOTICE.md
injective_py-1.12.0.dist-info/RECORD
