Metadata-Version: 2.4
Name: injective-py
Version: 1.12.0
Summary: Injective Python SDK, with Exchange API Client
License: Apache-2.0
License-File: LICENSE.md
License-File: NOTICE.md
Keywords: injective,blockchain,cosmos,injectivelabs
Author: Injective Labs
Author-email: contact@injectivelabs.org
Requires-Python: >=3.10,<4.0
Classifier: Intended Audience :: Developers
Classifier: License :: OSI Approved :: Apache Software License
Classifier: Programming Language :: Python :: 3
Classifier: Programming Language :: Python :: 3.10
Classifier: Programming Language :: Python :: 3.11
Classifier: Programming Language :: Python :: 3.12
Classifier: Programming Language :: Python :: 3.13
Classifier: Programming Language :: Python :: 3.14
Requires-Dist: aiohttp (>=3.9.4,<4.0.0)
Requires-Dist: bech32
Requires-Dist: bip32
Requires-Dist: ecdsa
Requires-Dist: eip712
Requires-Dist: grpcio
Requires-Dist: grpcio-tools
Requires-Dist: hdwallets
Requires-Dist: mnemonic
Requires-Dist: protobuf (>=5.26.1,<6.0.0)
Requires-Dist: requests
Requires-Dist: safe-pysha3
Requires-Dist: web3 (>=7.0.0,<8.0.0)
Requires-Dist: websockets
Project-URL: Documentation, https://api.injective.exchange/
Project-URL: Homepage, https://injectivelabs.org/
Project-URL: Repository, https://github.com/InjectiveLabs/sdk-python
